portstat
