Metadata-Version: 1.0
Name: portstat
Version: 0.0.6
Summary: A simple port traffic monitor
Home-page: https://github.com/imlonghao/portstat
Author: imlonghao
Author-email: shield@fastmail.com
License: Apache License 2.0
Keywords: port,monitor,traffic
Platform: any
